Metadata-Version: 2.1
Name: pyemgpipeline
Version: 1.0.0
Summary: EMG signal processing pipeline
Home-page: https://github.com/aalhossary/pyemgpipeline
Author: tlwu et al
Author-email: tlwu2008@gmail.com
License: UNKNOWN
Project-URL: API reference, https://aalhossary.github.io/pyemgpipeline/api.html
Project-URL: Bug Tracker, https://github.com/aalhossary/pyemgpipeline/issues
Platform: UNKNOWN
Classifier: Programming Language :: Python :: 3
Classifier: License :: OSI Approved :: GNU General Public License v3 (GPLv3)
Classifier: Operating System :: OS Independent
Requires-Python: >=3.6
License-File: LICENSE
Requires-Dist: numpy
Requires-Dist: scipy
Requires-Dist: matplotlib
